guardian/__init__.py
guardian/_default_value.py
guardian/custom_guard.py
guardian/guard.py
guardian/guard_utils.py
guardian/py.typed
guardian/atomic_guards/__init__.py
guardian/atomic_guards/any.py
guardian/atomic_guards/composites.py
guardian/atomic_guards/dates.py
guardian/atomic_guards/numbers.py
guardian/atomic_guards/strings.py
guardian_python-1.1.2.dist-info/LICENSE.md
guardian_python-1.1.2.dist-info/METADATA
guardian_python-1.1.2.dist-info/WHEEL
guardian_python-1.1.2.dist-info/top_level.txt
guardian_python-1.1.2.dist-info/RECORD
