Metadata-Version: 2.1
Name: guardian-python
Version: 1.1.2
Summary: Guard Clause Package
Home-page: https://github.com/RoeiOhayon/Guardian
Author: Roei Ohayon
Author-email: roeiohayon1652@gmail.com
Maintainer: Roei Ohayon
Project-URL: GitHub, https://github.com/RoeiOhayon/Guardian
License-File: LICENSE.md
